[{"OurCoords": [30, 50], "Callsign": "UAL202  ", "Heading": 251.06, "icao24": "aa8c39", "latitude": 38.1915, "longitude": -117.0055, "Country": "United States", "Velocity": 220.28}, {"OurCoords": [30, 50], "Callsign": "JST226  ", "Heading": 20.05, "icao24": "7c6b41", "latitude": -40.7147, "longitude": 173.9225, "Country": "Australia", "Velocity": 213.04}, {"OurCoords": [30, 50], "Callsign": "AIQ178  ", "Heading": 113.58, "icao24": "880457", "latitude": 14.1379, "longitude": 100.5538, "Country": "Thailand", "Velocity": 132.47}, {"OurCoords": [30, 50], "Callsign": "SWR122W ", "Heading": 205.23, "icao24": "4b1806", "latitude": 51.4624, "longitude": 9.3272, "Country": "Switzerland", "Velocity": 236.57}, {"OurCoords": [30, 50], "Callsign": "SWR272N ", "Heading": 310.97, "icao24": "4b1800", "latitude": 43.1175, "longitude": 19.8685, "Country": "Switzerland", "Velocity": 233.02}, {"OurCoords": [30, 50], "Callsign": "SAA058  ", "Heading": 325.73, "icao24": "00b22b", "latitude": -25.7653, "longitude": 27.9985, "Country": "South Africa", "Velocity": 197.34}, {"OurCoords": [30, 50], "Callsign": "ASA494  ", "Heading": 124.54, "icao24": "a2228b", "latitude": 46.4505, "longitude": -121.2826, "Country": "United States", "Velocity": 268.56}, {"OurCoords": [30, 50], "Callsign": "DLH43A  ", "Heading": 65.91, "icao24": "3c6664", "latitude": 49.0743, "longitude": 4.2223, "Country": "Germany", "Velocity": 250.78}, {"OurCoords": [30, 50], "Callsign": "SAA265  ", "Heading": 78, "icao24": "00b203", "latitude": 48.3481, "longitude": 11.7982, "Country": "South Africa", "Velocity": 5.14}, {"OurCoords": [30, 50], "Callsign": "SAA222  ", "Heading": 238.76, "icao24": "00b205", "latitude": -23.2704, "longitude": -45.9163, "Country": "South Africa", "Velocity": 146.81}, {"OurCoords": [30, 50], "Callsign": "DLH9923 ", "Heading": 88.06, "icao24": "3c6671", "latitude": 50.2015, "longitude": 8.1519, "Country": "Germany", "Velocity": 167.29}, {"OurCoords": [30, 50], "Callsign": "UAL1273 ", "Heading": 250.68, "icao24": "a39bfa", "latitude": 36.8718, "longitude": -125.5174, "Country": "United States", "Velocity": 240.96}, {"OurCoords": [30, 50], "Callsign": "DAL1812 ", "Heading": 228.62, "icao24": "ad566c", "latitude": 38.0039, "longitude": -78.958, "Country": "United States", "Velocity": 213.23}, {"OurCoords": [30, 50], "Callsign": "DAL779  ", "Heading": 232.51, "icao24": "adecb6", "latitude": 33.9078, "longitude": -93.4444, "Country": "United States", "Velocity": 208.77}, {"OurCoords": [30, 50], "Callsign": "ASA1158 ", "Heading": 172.82, "icao24": "abaceb", "latitude": 37.413, "longitude": -119.644, "Country": "United States", "Velocity": 210}, {"OurCoords": [30, 50], "Callsign": "VOE8UX  ", "Heading": 202.32, "icao24": "3455da", "latitude": 49.0205, "longitude": 2.7552, "Country": "Spain", "Velocity": 211.32}, {"OurCoords": [30, 50], "Callsign": "ACA711  ", "Heading": 304.41, "icao24": "c0225e", "latitude": 43.1838, "longitude": -79.1183, "Country": "Canada", "Velocity": 136.56}, {"OurCoords": [30, 50], "Callsign": "SWR86   ", "Heading": 267, "icao24": "4b1883", "latitude": 45.4615, "longitude": -73.7378, "Country": "Switzerland", "Velocity": 6.94}, {"OurCoords": [30, 50], "Callsign": "JBU975  ", "Heading": 198.24, "icao24": "a83e86", "latitude": 34.7292, "longitude": -77.3598, "Country": "United States", "Velocity": 236.7}, {"OurCoords": [30, 50], "Callsign": "SJE39   ", "Heading": 261.95, "icao24": "a09db5", "latitude": 35.3527, "longitude": -112.299, "Country": "United States", "Velocity": 202.11}, {"OurCoords": [30, 50], "Callsign": "DLH9JK  ", "Heading": 268.08, "icao24": "3c65c6", "latitude": 52.5897, "longitude": 13.6082, "Country": "Germany", "Velocity": 107.58}, {"OurCoords": [30, 50], "Callsign": "EWG5NA  ", "Heading": 146, "icao24": "3c5ee2", "latitude": 51.2829, "longitude": 6.7599, "Country": "Germany", "Velocity": 8.75}, {"OurCoords": [30, 50], "Callsign": "EWG860  ", "Heading": 175.3, "icao24": "3c5eed", "latitude": 43.6585, "longitude": 8.9284, "Country": "Germany", "Velocity": 238.48}, {"OurCoords": [30, 50], "Callsign": "DLH892  ", "Heading": 160, "icao24": "3c65cb", "latitude": 50.0435, "longitude": 8.5605, "Country": "Germany", "Velocity": 3.09}, {"OurCoords": [30, 50], "Callsign": "N241LM  ", "Heading": 307.84, "icao24": "a234bc", "latitude": 34.7496, "longitude": -117.6064, "Country": "United States", "Velocity": 84.69}, {"OurCoords": [30, 50], "Callsign": "AUA239  ", "Heading": 337.08, "icao24": "44020a", "latitude": 49.1332, "longitude": 15.4403, "Country": "Austria", "Velocity": 253.58}, {"OurCoords": [30, 50], "Callsign": "WZZ125  ", "Heading": 103.59, "icao24": "471eaa", "latitude": 53.2063, "longitude": -0.4922, "Country": "Hungary", "Velocity": 238.69}, {"OurCoords": [30, 50], "Callsign": "FRA23   ", "Heading": 247, "icao24": "3c4090", "latitude": 50.0413, "longitude": 8.5527, "Country": "Germany", "Velocity": 6.69}, {"OurCoords": [30, 50], "Callsign": "SCX8250 ", "Heading": 343.94, "icao24": "ab1628", "latitude": 43.11, "longitude": -96.5679, "Country": "United States", "Velocity": 215.74}, {"OurCoords": [30, 50], "Callsign": "JIA5312 ", "Heading": 104.34, "icao24": "a69b86", "latitude": 35.7819, "longitude": -82.9756, "Country": "United States", "Velocity": 232.58}, {"OurCoords": [30, 50], "Callsign": "AFL151  ", "Heading": 9.48, "icao24": "4248f8", "latitude": 26.9145, "longitude": -81.7734, "Country": "United Kingdom", "Velocity": 249.83}, {"OurCoords": [30, 50], "Callsign": "ASH5771 ", "Heading": 108.92, "icao24": "ac9731", "latitude": 36.4923, "longitude": -103.7061, "Country": "United States", "Velocity": 269.74}, {"OurCoords": [30, 50], "Callsign": "WJA2228 ", "Heading": 129.61, "icao24": "c03517", "latitude": 34.0836, "longitude": -85.0882, "Country": "Canada", "Velocity": 251.75}, {"OurCoords": [30, 50], "Callsign": "BMS8PA  ", "Heading": 86.95, "icao24": "4a09b0", "latitude": 46.4387, "longitude": 20.6559, "Country": "Romania", "Velocity": 231.83}, {"OurCoords": [30, 50], "Callsign": "BMS2933 ", "Heading": 296.4, "icao24": "4a09ae", "latitude": 48.7225, "longitude": 19.8303, "Country": "Romania", "Velocity": 239.5}, {"OurCoords": [30, 50], "Callsign": "ROU1915 ", "Heading": 220.71, "icao24": "c02202", "latitude": 44.0893, "longitude": -79.063, "Country": "Canada", "Velocity": 150.66}, {"OurCoords": [30, 50], "Callsign": "AFR771X ", "Heading": 161.17, "icao24": "393324", "latitude": 48.4864, "longitude": 2.3011, "Country": "France", "Velocity": 210.35}, {"OurCoords": [30, 50], "Callsign": "SAS1221 ", "Heading": 316.86, "icao24": "5110e7", "latitude": 55.7571, "longitude": 12.5718, "Country": "Estonia", "Velocity": 100.82}, {"OurCoords": [30, 50], "Callsign": "VIR127  ", "Heading": 200.17, "icao24": "4008f9", "latitude": 43.2867, "longitude": -70.6813, "Country": "United Kingdom", "Velocity": 247.71}, {"OurCoords": [30, 50], "Callsign": "AAL2363 ", "Heading": 126.25, "icao24": "a3ed91", "latitude": 37.581, "longitude": -105.5073, "Country": "United States", "Velocity": 248.8}, {"OurCoords": [30, 50], "Callsign": "N111RM  ", "Heading": 191.24, "icao24": "a0316d", "latitude": 31.8598, "longitude": -101.6224, "Country": "United States", "Velocity": 87.07}, {"OurCoords": [30, 50], "Callsign": "AAL1993 ", "Heading": 216.26, "icao24": "a16fa6", "latitude": 36.4392, "longitude": -79.6211, "Country": "United States", "Velocity": 222.66}, {"OurCoords": [30, 50], "Callsign": "SWR327  ", "Heading": 110.7, "icao24": "4b16b9", "latitude": 48.8255, "longitude": 2.7765, "Country": "Switzerland", "Velocity": 272.22}, {"OurCoords": [30, 50], "Callsign": "FFT536  ", "Heading": 92.01, "icao24": "a3b7cb", "latitude": 39.9692, "longitude": -87.6386, "Country": "United States", "Velocity": 264.59}, {"OurCoords": [30, 50], "Callsign": "GIA874  ", "Heading": 32.53, "icao24": "8a0452", "latitude": 5.6299, "longitude": 115.9743, "Country": "Indonesia", "Velocity": 261.16}, {"OurCoords": [30, 50], "Callsign": "GIA648  ", "Heading": 100.98, "icao24": "8a043a", "latitude": -6.3382, "longitude": 107.0334, "Country": "Indonesia", "Velocity": 191.8}, {"OurCoords": [30, 50], "Callsign": "3784    ", "Heading": 216.26, "icao24": "abc780", "latitude": 36.5561, "longitude": -79.515, "Country": "United States", "Velocity": 213.09}, {"OurCoords": [30, 50], "Callsign": "TRA86C  ", "Heading": 310.27, "icao24": "48597d", "latitude": 38.4171, "longitude": 22.8067, "Country": "Kingdom of the Netherlands", "Velocity": 225.21}, {"OurCoords": [30, 50], "Callsign": "SWR225U ", "Heading": 229.63, "icao24": "4b16ba", "latitude": 47.5147, "longitude": 9.0485, "Country": "Switzerland", "Velocity": 126.27}, {"OurCoords": [30, 50], "Callsign": "N9713F  ", "Heading": 32.86, "icao24": "ad8a23", "latitude": 32.981, "longitude": -112.1399, "Country": "United States", "Velocity": 58.79}, {"OurCoords": [30, 50], "Callsign": "AEA7137 ", "Heading": 206.21, "icao24": "344459", "latitude": 33.7461, "longitude": -12.7969, "Country": "Spain", "Velocity": 223.63}, {"OurCoords": [30, 50], "Callsign": "ROU1703 ", "Heading": 318.84, "icao24": "c04811", "latitude": 44.3199, "longitude": -78.5806, "Country": "Canada", "Velocity": 125.05}, {"OurCoords": [30, 50], "Callsign": "DLH9TW  ", "Heading": 261, "icao24": "3c6744", "latitude": 48.3563, "longitude": 11.7924, "Country": "Germany", "Velocity": 0}, {"OurCoords": [30, 50], "Callsign": "DLH57F  ", "Heading": 250, "icao24": "3c6747", "latitude": 50.0378, "longitude": 8.5414, "Country": "Germany", "Velocity": 12.35}, {"OurCoords": [30, 50], "Callsign": "2971    ", "Heading": 269.71, "icao24": "a5d1f7", "latitude": 33.4921, "longitude": -87.5749, "Country": "United States", "Velocity": 206.29}, {"OurCoords": [30, 50], "Callsign": "FFT1018 ", "Heading": 104.51, "icao24": "a99a52", "latitude": 30.2879, "longitude": -96.0671, "Country": "United States", "Velocity": 240.19}, {"OurCoords": [30, 50], "Callsign": "DLH62A  ", "Heading": 263.62, "icao24": "3c6741", "latitude": 48.3582, "longitude": 11.9797, "Country": "Germany", "Velocity": 78.68}, {"OurCoords": [30, 50], "Callsign": "AZU5479 ", "Heading": 214.31, "icao24": "e4936a", "latitude": -8.4015, "longitude": -36.3805, "Country": "Brazil", "Velocity": 237.29}, {"OurCoords": [30, 50], "Callsign": "WZZ14   ", "Heading": 70.91, "icao24": "471f72", "latitude": 53.9866, "longitude": 23.1634, "Country": "Hungary", "Velocity": 199.79}, {"OurCoords": [30, 50], "Callsign": "EJU95ZU ", "Heading": 70.19, "icao24": "4400b7", "latitude": 49.1914, "longitude": 4.2972, "Country": "Austria", "Velocity": 244.42}, {"OurCoords": [30, 50], "Callsign": "AMX484  ", "Heading": 322.65, "icao24": "0d0b76", "latitude": 35.5683, "longitude": -114.2206, "Country": "Mexico", "Velocity": 172.14}, {"OurCoords": [30, 50], "Callsign": "        ", "Heading": 70, "icao24": "3c675a", "latitude": 50.0405, "longitude": 8.5596, "Country": "Germany", "Velocity": 7.72}, {"OurCoords": [30, 50], "Callsign": "WZZ234  ", "Heading": 241.76, "icao24": "471f2f", "latitude": 43.7687, "longitude": 6.6747, "Country": "Hungary", "Velocity": 211.98}, {"OurCoords": [30, 50], "Callsign": "N444DT  ", "Heading": 80.92, "icao24": "a559d6", "latitude": 32.8667, "longitude": -96.8333, "Country": "United States", "Velocity": 88.04}, {"OurCoords": [30, 50], "Callsign": "WZZ519  ", "Heading": 295.58, "icao24": "471f54", "latitude": 50.4154, "longitude": 12.8538, "Country": "Hungary", "Velocity": 240.69}, {"OurCoords": [30, 50], "Callsign": "EJM609  ", "Heading": 217.94, "icao24": "a00986", "latitude": 33.9766, "longitude": -79.0461, "Country": "United States", "Velocity": 236.79}, {"OurCoords": [30, 50], "Callsign": "AAY8023 ", "Heading": 99.14, "icao24": "a36980", "latitude": 31.3818, "longitude": -99.5075, "Country": "United States", "Velocity": 255.84}, {"OurCoords": [30, 50], "Callsign": "NDU604  ", "Heading": 325.27, "icao24": "a7d74b", "latitude": 33.0026, "longitude": -111.514, "Country": "United States", "Velocity": 55.08}, {"OurCoords": [30, 50], "Callsign": "SYL772  ", "Heading": 49.63, "icao24": "42499a", "latitude": 56.049, "longitude": 43.7455, "Country": "United Kingdom", "Velocity": 234.3}, {"OurCoords": [30, 50], "Callsign": "00AC5XA0", "Heading": 243.55, "icao24": "0d0b1d", "latitude": 29.2066, "longitude": -95.3068, "Country": "Mexico", "Velocity": 220.63}, {"OurCoords": [30, 50], "Callsign": "N500EH  ", "Heading": 129.37, "icao24": "a63a5c", "latitude": 60.7421, "longitude": -151.3235, "Country": "United States", "Velocity": 25.95}, {"OurCoords": [30, 50], "Callsign": "ARG1244 ", "Heading": 50.31, "icao24": "e07542", "latitude": -32.4942, "longitude": -54.4368, "Country": "Argentina", "Velocity": 219.93}, {"OurCoords": [30, 50], "Callsign": "DPJ604  ", "Heading": 353.79, "icao24": "a7d771", "latitude": 31.1285, "longitude": -81.8291, "Country": "United States", "Velocity": 218.89}, {"OurCoords": [30, 50], "Callsign": "HBAL602 ", "Heading": 206.57, "icao24": "a3693c", "latitude": -5.2683, "longitude": -76.3866, "Country": "United States", "Velocity": 1.15}, {"OurCoords": [30, 50], "Callsign": "QFA36   ", "Heading": 151.77, "icao24": "7c4921", "latitude": -35.465, "longitude": 143.586, "Country": "Australia", "Velocity": 238.22}, {"OurCoords": [30, 50], "Callsign": "GLO7717 ", "Heading": 110.72, "icao24": "e48c05", "latitude": -22.6307, "longitude": -47.4468, "Country": "Brazil", "Velocity": 212.31}, {"OurCoords": [30, 50], "Callsign": "UAL682  ", "Heading": 99.48, "icao24": "a533bd", "latitude": 41.1613, "longitude": -77.7103, "Country": "United States", "Velocity": 284.25}, {"OurCoords": [30, 50], "Callsign": "AAF264  ", "Heading": 0.26, "icao24": "39968b", "latitude": 37.4546, "longitude": -0.0195, "Country": "France", "Velocity": 229.96}, {"OurCoords": [30, 50], "Callsign": "N511TP  ", "Heading": 311.52, "icao24": "a666dd", "latitude": 33.8079, "longitude": -117.6107, "Country": "United States", "Velocity": 90.02}, {"OurCoords": [30, 50], "Callsign": "ACA018  ", "Heading": 135.89, "icao24": "c02ec7", "latitude": 49.7856, "longitude": -123.8864, "Country": "Canada", "Velocity": 233.57}, {"OurCoords": [30, 50], "Callsign": "N4540D  ", "Heading": 346.66, "icao24": "a58354", "latitude": 32.7199, "longitude": -96.3512, "Country": "United States", "Velocity": 82.48}, {"OurCoords": [30, 50], "Callsign": "AAL2244 ", "Heading": 206.77, "icao24": "ad574f", "latitude": 41.7287, "longitude": -87.9591, "Country": "United States", "Velocity": 126.77}, {"OurCoords": [30, 50], "Callsign": "SKV7675 ", "Heading": 272.71, "icao24": "c035bb", "latitude": 43.0743, "longitude": -76.2063, "Country": "Canada", "Velocity": 217.85}, {"OurCoords": [30, 50], "Callsign": "N7096L  ", "Heading": 51.04, "icao24": "a97932", "latitude": 33.6719, "longitude": -117.709, "Country": "United States", "Velocity": 31.09}, {"OurCoords": [30, 50], "Callsign": "TE24    ", "Heading": 300, "icao24": "4b5da5", "latitude": 47.461, "longitude": 8.5584, "Country": "Switzerland", "Velocity": 6.43}, {"OurCoords": [30, 50], "Callsign": "TE21    ", "Heading": 303, "icao24": "4b5da2", "latitude": 47.4517, "longitude": 8.5566, "Country": "Switzerland", "Velocity": 4.89}, {"OurCoords": [30, 50], "Callsign": "SKW1367 ", "Heading": 261.43, "icao24": "a6192b", "latitude": 39.7321, "longitude": -86.3418, "Country": "United States", "Velocity": 179.49}, {"OurCoords": [30, 50], "Callsign": "DAL1622 ", "Heading": 303.65, "icao24": "a4503d", "latitude": 35.5192, "longitude": -114.3071, "Country": "United States", "Velocity": 214.45}, {"OurCoords": [30, 50], "Callsign": "UAL1106 ", "Heading": 95.11, "icao24": "a61949", "latitude": 31.1476, "longitude": -100.9493, "Country": "United States", "Velocity": 259.8}, {"OurCoords": [30, 50], "Callsign": "N6981E  ", "Heading": 228.81, "icao24": "a94aee", "latitude": 38.0014, "longitude": -122.5369, "Country": "United States", "Velocity": 54.69}, {"OurCoords": [30, 50], "Callsign": "SKW5394 ", "Heading": 165.36, "icao24": "a0808f", "latitude": 34.956, "longitude": -119.2215, "Country": "United States", "Velocity": 213.74}, {"OurCoords": [30, 50], "Callsign": "GLO1172 ", "Heading": 252.91, "icao24": "e48c30", "latitude": -23.6511, "longitude": -46.7433, "Country": "Brazil", "Velocity": 187.3}, {"OurCoords": [30, 50], "Callsign": "AZU5069 ", "Heading": 129.53, "icao24": "e49311", "latitude": -20.9918, "longitude": -50.7801, "Country": "Brazil", "Velocity": 244.11}, {"OurCoords": [30, 50], "Callsign": "SKW5967 ", "Heading": 296.95, "icao24": "a1b519", "latitude": 37.6118, "longitude": -122.3587, "Country": "United States", "Velocity": 69.25}, {"OurCoords": [30, 50], "Callsign": "N136PA  ", "Heading": 271.47, "icao24": "a092c1", "latitude": 32.0162, "longitude": -99.3565, "Country": "United States", "Velocity": 120.42}]